{
  "user": [
    {
      "id": 1,
      "username": "a1",
      "password": "a1"
    },
    {
      "id": 2,
      "username": "a2",
      "password": "a2"
    },
    {
      "id": 3,
      "username": "a3",
      "password": "a3"
    }
  ],
  "todos": [
    {
      "title": "title 1",
      "complate": false,
      "id": 1
    },
    {
      "title": "title 2",
      "complate": false,
      "id": 2
    },
    {
      "title": "title 3",
      "complate": false,
      "id": 3
    },
    {
      "title": " title 4",
      "complate": false,
      "id": 4
    },
    {
      "title": "title 5",
      "complate": false,
      "id": 5
    }
  ]
}